decoder.t.v
// Decoder testbench
`timescale 1 ns / 1 ps
`include "decoder.v"

module testDecoder (); 
    reg addr0, addr1;
    reg enable;
    wire out0,out1,out2,out3;

    //behavioralDecoder decoder (out0,out1,out2,out3,addr0,addr1,enable);
    structuralDecoder decoder (out0,out1,out2,out3,addr0,addr1,enable); // Swap after testing

    initial begin
    $dumpfile("decoder.vcd");
    $dumpvars();

    $display("En A0 A1| O0 O1 O2 O3 | Expected Output");
    enable=0;addr0=0;addr1=0; #1000 
    $display("%b  %b  %b |  %b  %b  %b  %b | All false", enable, addr0, addr1, out0, out1, out2, out3);
    enable=0;addr0=1;addr1=0; #1000
    $display("%b  %b  %b |  %b  %b  %b  %b | All false", enable, addr0, addr1, out0, out1, out2, out3);
    enable=0;addr0=0;addr1=1; #1000 
    $display("%b  %b  %b |  %b  %b  %b  %b | All false", enable, addr0, addr1, out0, out1, out2, out3);
    enable=0;addr0=1;addr1=1; #1000 
    $display("%b  %b  %b |  %b  %b  %b  %b | All false", enable, addr0, addr1, out0, out1, out2, out3);
    enable=1;addr0=0;addr1=0; #1000 
    $display("%b  %b  %b |  %b  %b  %b  %b | O0 Only", enable, addr0, addr1, out0, out1, out2, out3);
    enable=1;addr0=1;addr1=0; #1000 
    $display("%b  %b  %b |  %b  %b  %b  %b | O1 Only", enable, addr0, addr1, out0, out1, out2, out3);
    enable=1;addr0=0;addr1=1; #1000 
    $display("%b  %b  %b |  %b  %b  %b  %b | O2 Only", enable, addr0, addr1, out0, out1, out2, out3);
    enable=1;addr0=1;addr1=1; #1000 
    $display("%b  %b  %b |  %b  %b  %b  %b | O3 Only", enable, addr0, addr1, out0, out1, out2, out3);
    $finish();
    end

endmodule

decoder.v
// Decoder circuit
`define AND and #50
`define OR or #50
`define NOT not #50

module behavioralDecoder (
	output out0, out1, out2, out3,
	input  address0, address1,
	input  enable
);
	// Uses concatenation and shift operators
	assign {out3,out2,out1,out0}=enable<<{address1,address0};
endmodule


module structuralDecoder
(
    output out0, out1, out2, out3,
    input address0, address1,
    input enable
);

	wire nA0, nA1, nA0andnA1, A0andnA1, nA0andA1, A0andA1; 

	`NOT nA0gate(nA0,address0);
	`NOT nA1gate(nA1,address1);

	`AND nA0nA1gate(nA0andnA1, nA0, nA1);
	`AND A0nA1gate(A0andnA1, address0,nA1);
	`AND nA0A1gate(nA0andA1, nA0, address1);
	`AND A0A1gate(A0andA1,address0,address1);

	`AND ennA0nA1gate(out0,nA0andnA1,enable);
	`AND enA0nA1gate(out1,A0andnA1,enable);
	`AND ennA0A1gate(out2,nA0andA1,enable);
	`AND enA0A1gate(out3,A0andA1,enable);

endmodule

decoder.vcd
$date
	Thu Sep 20 23:10:25 2018
$end
$version
	Icarus Verilog
$end
$timescale
	1ps
$end
$scope module behavioralDecoder $end
$var wire 1 ! address0 $end
$var wire 1 " address1 $end
$var wire 1 # enable $end
$var wire 1 $ out3 $end
$var wire 1 % out2 $end
$var wire 1 & out1 $end
$var wire 1 ' out0 $end
$upscope $end
$scope module testDecoder $end
$var wire 1 ( out3 $end
$var wire 1 ) out2 $end
$var wire 1 * out1 $end
$var wire 1 + out0 $end
$var reg 1 , addr0 $end
$var reg 1 - addr1 $end
$var reg 1 . enable $end
$scope module decoder $end
$var wire 1 / A0andA1 $end
$var wire 1 0 A0andnA1 $end
$var wire 1 , address0 $end
$var wire 1 - address1 $end
$var wire 1 . enable $end
$var wire 1 1 nA0 $end
$var wire 1 2 nA0andA1 $end
$var wire 1 3 nA0andnA1 $end
$var wire 1 4 nA1 $end
$var wire 1 + out0 $end
$var wire 1 * out1 $end
$var wire 1 ) out2 $end
$var wire 1 ( out3 $end
$upscope $end
$upscope $end
$enddefinitions $end
#0
$dumpvars
x4
x3
x2
x1
x0
x/
0.
0-
0,
x+
x*
x)
x(
x'
x&
x%
x$
z#
z"
z!
$end
#50000
14
11
0(
0)
0*
0+
0/
02
00
#100000
13
#1000000
1,
#1050000
01
10
#1100000
03
#2000000
1-
0,
#2050000
04
11
00
#2100000
12
#3000000
1,
#3050000
01
1/
#3100000
02
#4000000
0-
0,
1.
#4050000
14
11
0/
1(
#4100000
13
0(
#4150000
1+
#5000000
1,
#5050000
01
10
#5100000
03
1*
#5150000
0+
#6000000
1-
0,
#6050000
04
11
00
#6100000
12
0*
#6150000
1)
#7000000
1,
#7050000
01
1/
#7100000
02
1(
#7150000
0)
